discordrp/__init__.py
discordrp/presence.py
discordrp/py.typed
discord_rich_presence-1.0.3.dist-info/LICENSE
discord_rich_presence-1.0.3.dist-info/METADATA
discord_rich_presence-1.0.3.dist-info/WHEEL
discord_rich_presence-1.0.3.dist-info/top_level.txt
discord_rich_presence-1.0.3.dist-info/RECORD
